{
  "name": "Фокус охоты",
  "icon": "goety:hunting_focus",
  "category": "goety:focuses/wild",
  "pages": [
    {
      "type": "patchouli:text",
      "text": "Чёрные волки — это сверхъестественные демонические гончие, упоминаемые в фольклоре, которых можно увидеть в обычном мире. С помощью фокуса вы можете призвать их на помощь. При использовании $(l:crafts/wild_staff)дикого посоха$() создаётся больше волков, а дикая мантия усиливает их так, что их когти и укусы проклинают жертву."
    },
    {
      "type": "patchouli:crafting",
      "recipe": "goety:focus/hunting_focus"
    }
  ]
}