{
  "name": "不详镰刀",
  "icon": "goety:dark_scythe",
  "category": "goety:crafts/equipment",
  "pages": [
    {
      "type": "patchouli:text",
      "text": "不详镰刀是一种强大的武器，它每次攻击都能击中多个生物。它不仅有很强大的打击，而且持用者每次击中生物都会获得灵魂能量。如果持用者的攻击冷却已满，镰刀将以更大的半径横扫生物，尽管需要很长一段时间才能恢复，如果你副手没有任何东西，那么攻击冷却会减半。"
    },
    {
      "type": "goety:ritual",
      "recipe": "goety:dark_scythe"
    },
    {
      "type": "patchouli:text",
      "text": "镰刀可以在铁砧上用 $(l:intro/magical_components)诅咒金属锭$()修复，但是别忘记了，它本质依然是把大镰刀，也可以用作清除杂草或大面积收割作物的工具，它甚至可以不用精准采集直接采集到幽匿块。"
    }
  ]
}