{
  "type": "goety:ritual",
  "ritual_type": "goety:craft",
  "activation_item": {
    "item": "goety:animation_core"
  },
  "craftType": "animation",
  "soulCost": 5,
  "duration": 30,
  "ingredients": [
    {
      "item": "minecraft:amethyst_block"
    },
    {
      "item": "minecraft:ender_pearl"
    },
    {
      "item": "minecraft:anvil"
    },
    {
      "item": "minecraft:note_block"
    },
    {
      "item": "minecraft:sculk_sensor"
    },
    {
      "item": "minecraft:blaze_rod"
    },
    {
      "item": "minecraft:feather"
    },
    {
      "item": "minecraft:glowstone_dust"
    }
  ],
  "result": {
    "item": "goety:vexing_focus"
  }
}