{
  "name": "仆人属性",
  "icon": "goety:zombie_servant_spawn_egg",
  "category": "goety:summons",
  "sortnum": 0,
  "pages": [
    {
      "type": "patchouli:text",
      "text": "被仪式或咒语召唤的仆人往往会彼此共享一些属性。首先，他们会主动攻击各种敌对生物，如果他们共享一个召唤师，他们不会互相攻击，他们的寿命有限，一个召唤师能有多少仆人也是有限制的。"
    },
    {
      "type": "patchouli:text",
      "text": "然而，如果召唤者戴上死灵王冠，亡灵仆人就会永远存在；如果召唤者戴着死灵斗篷，他们可以使用召唤者的灵魂能量来治愈自己（前提是他们没有着火）。不死从者在不戴头盔时会在阳光下燃烧。"
    },
    {
      "type": "patchouli:text",
      "text": "如果召唤者的魔杖上配备了焦点并在蹲伏时施展法术，不死仆人可以传送到召唤者身边。如果召唤的仆人不是 Vex，用魔杖/法杖击中它们（或者，如果通过配置启用，右键单击它们）将使它们跟随召唤者，在该区域徘徊或留在原地。"
    }
  ]
}