{
  "type": "goety:ritual",
  "ritual_type": "goety:enchant",
  "activation_item": {
    "item": "minecraft:book"
  },
  "craftType": "magic",
  "soulCost": 10,
  "duration": 10,
  "enchantment": "minecraft:binding_curse",
  "xpLevelCost": 5,
  "ingredients": [
    {
      "item": "minecraft:iron_bars"
    },
    {
      "item": "minecraft:iron_bars"
    },
    {
      "item": "minecraft:iron_bars"
    },
    {
      "item": "minecraft:iron_bars"
    },
    {
      "tag": "forge:gems/lapis"
    }
  ],
  "result": {
    "item": "minecraft:enchanted_book"
  }
}