{
  "name": "Морозные одежды",
  "icon": "goety:frost_robe",
  "category": "goety:crafts/garment",
  "pages": [
    {
      "type": "patchouli:text",
      "text": "Морозная мантия наделяет своего владельца силой холода. Те, кто её носит, никогда не замёрзнут, будут устойчивы к ледяным атакам и смогут свободно передвигаться по рыхлому снегу. Кроме того, мантия делает морозные заклинания дешевле."
    },
    {
      "type": "goety:ritual",
      "recipe": "goety:frost_robe"
    },
    {
      "type": "goety:ritual",
      "recipe": "goety:frost_crown"
    },
    {
      "type": "patchouli:text",
      "text": "Морозная корона вдвое сокращает время использования морозных заклинаний и не даёт вашим морозным прислужникам исчезать, подобно врединам."
    }
  ],
  "extra_recipe_mappings": {
    "goety:frost_robe": 1,
    "goety:frost_robe_cryo": 1,
    "goety:frost_crown": 2
  }
}